snirk/__init__.py
snirk/api.py
snirk/constants.py
snirk/fs.py
snirk/py.typed
snirk/sni/__init__.py
snirk/sni/sni_pb2.py
snirk/sni/sni_pb2.pyi
snirk/sni/sni_pb2_grpc.py
snirk/sni/version.txt
snirk/types.py
snirk-0.2.1.dist-info/LICENSE
snirk-0.2.1.dist-info/METADATA
snirk-0.2.1.dist-info/WHEEL
snirk-0.2.1.dist-info/RECORD
