Metadata-Version: 2.1
Name: snirk
Version: 0.2.1
Summary: Python wrapper for SNES Interface (SNI) gRPC API providing typed async interfaces.
Home-page: https://github.com/coffeemancy/snirk
License: GPL-3.0-or-later
Author: C
Author-email: mxcoffeemancy@gmail.com
Requires-Python: >=3.11,<4.0
Classifier: Development Status :: 4 - Beta
Classifier: Intended Audience :: Developers
Classifier: License :: OSI Approved :: GNU General Public License v3 or later (GPLv3+)
Classifier: Programming Language :: Python :: 3
Classifier: Programming Language :: Python :: 3.11
Requires-Dist: grpcio (>=1.60.1,<2.0.0)
Requires-Dist: protobuf (>=4.25.3,<5.0.0)
Project-URL: Repository, https://github.com/coffeemancy/snirk
